mcp_imgutils/__init__.py
mcp_imgutils/__main__.py
mcp_imgutils/server.py
mcp_imgutils/analysis/__init__.py
mcp_imgutils/analysis/utils.py
mcp_imgutils/analysis/viewer.py
mcp_imgutils/common/__init__.py
mcp_imgutils/common/cached_resource_manager.py
mcp_imgutils/common/config.py
mcp_imgutils/common/config_validator.py
mcp_imgutils/common/disk_resource_manager.py
mcp_imgutils/common/error_messages.py
mcp_imgutils/common/errors.py
mcp_imgutils/common/memory_cache.py
mcp_imgutils/common/rate_limiter.py
mcp_imgutils/common/resource_factory.py
mcp_imgutils/common/resource_manager.py
mcp_imgutils/common/retry.py
mcp_imgutils/generation/__init__.py
mcp_imgutils/generation/base.py
mcp_imgutils/generation/registry.py
mcp_imgutils/generation/bfl/__init__.py
mcp_imgutils/generation/bfl/client.py
mcp_imgutils/generation/bfl/config.py
mcp_imgutils/generation/bfl/framework_generator.py
mcp_imgutils/generation/bfl/generator.py
mcp_imgutils/generation/openai/__init__.py
mcp_imgutils/generation/openai/config.py
mcp_imgutils/generation/openai/framework_generator.py
mcp_imgutils/generation/openai/generator.py
mcp_imgutils-5.2.0.dist-info/METADATA
mcp_imgutils-5.2.0.dist-info/WHEEL
mcp_imgutils-5.2.0.dist-info/entry_points.txt
mcp_imgutils-5.2.0.dist-info/RECORD
