Metadata-Version: 2.4
Name: mcp-imgutils
Version: 5.2.0
Summary: MCP服务：将本地图片和网络图片发送给LLM
Requires-Python: >=3.11
Requires-Dist: aiofiles
Requires-Dist: anyio
Requires-Dist: click
Requires-Dist: httpx
Requires-Dist: mcp>=1.2.0
Requires-Dist: openai
Requires-Dist: pillow
Requires-Dist: requests
Requires-Dist: starlette
Requires-Dist: uvicorn
Provides-Extra: test
Requires-Dist: pre-commit>=3.6.0; extra == 'test'
Requires-Dist: pytest-asyncio>=0.23.0; extra == 'test'
Requires-Dist: pytest-cov>=4.1.0; extra == 'test'
Requires-Dist: pytest>=7.0.0; extra == 'test'
Requires-Dist: ruff>=0.3.0; extra == 'test'
